cli/__init__.py
cli/crm.py
cli/libs/__init__.py
cli/libs/helper.py
cli/libs/manager.py
cr_manager-3.0.5.dist-info/METADATA
cr_manager-3.0.5.dist-info/WHEEL
cr_manager-3.0.5.dist-info/entry_points.txt
cr_manager-3.0.5.dist-info/licenses/LICENSE
cr_manager-3.0.5.dist-info/RECORD
