Metadata-Version: 2.4
Name: cr-manager
Version: 3.0.5
Summary: Tool to automatically add, update, or delete multi-format copyright headers
License: MIT
License-File: LICENSE
Keywords: copyright,license
Author: marslo
Author-email: marslo.jiao@gmail.com
Requires-Python: >=3.10
Classifier: License :: OSI Approved :: MIT License
Classifier: Programming Language :: Python :: 3
Classifier: Programming Language :: Python :: 3.10
Classifier: Programming Language :: Python :: 3.11
Classifier: Programming Language :: Python :: 3.12
Classifier: Programming Language :: Python :: 3.13
Classifier: Programming Language :: Python :: 3.14
Requires-Dist: wcwidth (>=0.2.13,<0.3.0)
Project-URL: Documentation, https://github.com/marslo/cr-manager#readme
Project-URL: Homepage, https://pypi.org/project/cr-manager/
Project-URL: Repository, https://github.com/marslo/cr-manager
